Metadata-Version: 2.1
Name: botw-save-editor
Version: 2.0.2
Summary: A program for converting data between JSON and .sav file formats.
Home-page: https://github.com/SDarkMagic/botw-save-editor
Author: SDarkMagic
Author-email: TheSDarkMagic@gmail.com
License: UNKNOWN
Platform: UNKNOWN
Classifier: Programming Language :: Python :: 3
Classifier: License :: OSI Approved :: GNU General Public License (GPL)
Classifier: Operating System :: OS Independent
Requires-Python: >=3.7
